LogFusion/__init__.py
LogFusion/logfusion.py
LogFusion/logger.py
LogFusion/main.py
LogFusion/reader.py
LogFusion/runner.py
LogFusion/spinner.py
LogFusion-0.1.1.dist-info/LICENSE
LogFusion-0.1.1.dist-info/METADATA
LogFusion-0.1.1.dist-info/WHEEL
LogFusion-0.1.1.dist-info/entry_points.txt
LogFusion-0.1.1.dist-info/top_level.txt
LogFusion-0.1.1.dist-info/RECORD
